LICENSE
MANIFEST.in
setup.py
turtlelexer.py
TurtleLexer.egg-info/PKG-INFO
TurtleLexer.egg-info/SOURCES.txt
TurtleLexer.egg-info/dependency_links.txt
TurtleLexer.egg-info/entry_points.txt
TurtleLexer.egg-info/requires.txt
TurtleLexer.egg-info/top_level.txt