Metadata-Version: 1.0
Name: TurtleLexer
Version: 0.1
Summary: A Turtle lexer for Pygments
Home-page: https://github.com/kierdavis/TurtleLexer
Author: Kier Davis
Author-email: kierdavis@gmail.com
License: UNKNOWN
Keywords: pygments lexer turtle rdf
Platform: UNKNOWN
Classifier: Programming Language :: Python
Classifier: Operating System :: OS Independent
Classifier: Topic :: Software Development :: Libraries :: Python Modules
